medialpy/__init__.py
medialpy/abbrv.json.gz
tests/__init__.py
tests/test_medialpy.py
medialpy-0.0.4.dist-info/LICENSE
medialpy-0.0.4.dist-info/METADATA
medialpy-0.0.4.dist-info/WHEEL
medialpy-0.0.4.dist-info/top_level.txt
medialpy-0.0.4.dist-info/RECORD
