Metadata-Version: 2.1
Name: medialpy
Version: 0.0.4
Summary: MEDIcal Abbreviations Lookup in Python
Home-page: https://github.com/AberystwythSystemsBiology/medialpy
Author: KeironO
Author-email: keiron.oshea@wales.nhs.uk
License: UNKNOWN
Platform: UNKNOWN
License-File: LICENSE
